package1/__init__.py
package2/__init__.py
package3/__init__.py
MyPackage_112-0.0.1.dist-info/METADATA
MyPackage_112-0.0.1.dist-info/WHEEL
MyPackage_112-0.0.1.dist-info/top_level.txt
MyPackage_112-0.0.1.dist-info/RECORD
