Metadata-Version: 2.1
Name: MyPackage-112
Version: 0.0.1
Summary: This is my Package
Home-page: UNKNOWN
Author: Me
License: UNKNOWN
Platform: UNKNOWN
